pwny/__init__.py
pwny/bc.py
pwny/sc.py
pwnypack/__init__.py
pwnypack/asm.py
pwnypack/bytecode.py
pwnypack/codec.py
pwnypack/elf.py
pwnypack/flow.py
pwnypack/fmtstring.py
pwnypack/ipython_ext.py
pwnypack/main.py
pwnypack/marshal.py
pwnypack/oracle.py
pwnypack/packing.py
pwnypack/php.py
pwnypack/pickle.py
pwnypack/pwnbook.py
pwnypack/py_internals.py
pwnypack/rop.py
pwnypack/shell.py
pwnypack/target.py
pwnypack/util.py
pwnypack/shellcode/__init__.py
pwnypack/shellcode/base.py
pwnypack/shellcode/linux.py
pwnypack/shellcode/mutable_data.py
pwnypack/shellcode/ops.py
pwnypack/shellcode/stack_data.py
pwnypack/shellcode/translate.py
pwnypack/shellcode/types.py
pwnypack/shellcode/aarch64/__init__.py
pwnypack/shellcode/aarch64/linux.py
pwnypack/shellcode/arm/__init__.py
pwnypack/shellcode/arm/linux.py
pwnypack/shellcode/arm/thumb.py
pwnypack/shellcode/arm/thumb_mixed.py
pwnypack/shellcode/x86/__init__.py
pwnypack/shellcode/x86/linux.py
pwnypack/shellcode/x86/mutable_data.py
pwnypack/shellcode/x86/null_safe.py
pwnypack/shellcode/x86/stack_data.py
pwnypack/shellcode/x86_64/__init__.py
pwnypack/shellcode/x86_64/linux.py
pwnypack/shellcode/x86_64/null_safe.py
pwnypack/shellcode/x86_64/stack_data.py
pwnypack-0.9.0.dist-info/DESCRIPTION.rst
pwnypack-0.9.0.dist-info/METADATA
pwnypack-0.9.0.dist-info/RECORD
pwnypack-0.9.0.dist-info/WHEEL
pwnypack-0.9.0.dist-info/entry_points.txt
pwnypack-0.9.0.dist-info/metadata.json
pwnypack-0.9.0.dist-info/top_level.txt
