Metadata-Version: 1.1
Name: pwnypack
Version: 0.9.0
Summary: Official Certified Edible Dinosaurs CTF toolkit.
Home-page: https://github.com/edibledinos/pwnypack/
Author: Ingmar Steen
Author-email: iksteen@gmail.com
License: UNKNOWN
Download-URL: https://github.com/edibledinos/pwnypack/tarball/v0.9.0
Keywords: wargame,ctf
Platform: UNKNOWN
Classifier: Environment :: Console
Classifier: Intended Audience :: Developers
Classifier: Intended Audience :: Science/Research
Classifier: Intended Audience :: System Administrators
Classifier: License :: OSI Approved :: MIT License
Classifier: Operating System :: OS Independent
Classifier: Programming Language :: Python
Classifier: Programming Language :: Python :: 2
Classifier: Programming Language :: Python :: 3
Classifier: Topic :: Security
Classifier: Topic :: Security :: Cryptography
